MercurialShiyongJiaocheng/README.md
MercurialShiyongJiaocheng/__init__.py
MercurialShiyongJiaocheng/__main__.py
MercurialShiyongJiaocheng/file.epub
MercurialShiyongJiaocheng/index.html
MercurialShiyongJiaocheng/css/__init__.py
MercurialShiyongJiaocheng/css/annotations.css
MercurialShiyongJiaocheng/css/main.css
MercurialShiyongJiaocheng/css/normalize.css
MercurialShiyongJiaocheng/css/popup.css
MercurialShiyongJiaocheng/font/__init__.py
MercurialShiyongJiaocheng/font/fontello.eot
MercurialShiyongJiaocheng/font/fontello.svg
MercurialShiyongJiaocheng/font/fontello.ttf
MercurialShiyongJiaocheng/font/fontello.woff
MercurialShiyongJiaocheng/img/__init__.py
MercurialShiyongJiaocheng/img/annotator-glyph-sprite.png
MercurialShiyongJiaocheng/img/annotator-icon-sprite.png
MercurialShiyongJiaocheng/img/apple-touch-icon.png
MercurialShiyongJiaocheng/img/cancelfullscreen.png
MercurialShiyongJiaocheng/img/close.png
MercurialShiyongJiaocheng/img/fullscreen.png
MercurialShiyongJiaocheng/img/loader.gif
MercurialShiyongJiaocheng/img/menu-icon.png
MercurialShiyongJiaocheng/img/save.png
MercurialShiyongJiaocheng/img/saved.png
MercurialShiyongJiaocheng/img/settings-s.png
MercurialShiyongJiaocheng/img/settings.png
MercurialShiyongJiaocheng/img/star.png
MercurialShiyongJiaocheng/js/__init__.py
MercurialShiyongJiaocheng/js/epub.js
MercurialShiyongJiaocheng/js/epub.min.js
MercurialShiyongJiaocheng/js/epub.min.map
MercurialShiyongJiaocheng/js/hooks.min.js
MercurialShiyongJiaocheng/js/hooks.min.map
MercurialShiyongJiaocheng/js/reader.js
MercurialShiyongJiaocheng/js/reader.js.map
MercurialShiyongJiaocheng/js/reader.min.js
MercurialShiyongJiaocheng/js/reader.min.map
MercurialShiyongJiaocheng/js/hooks/__init__.py
MercurialShiyongJiaocheng/js/hooks/extensions/__init__.py
MercurialShiyongJiaocheng/js/hooks/extensions/highlight.js
MercurialShiyongJiaocheng/js/libs/__init__.py
MercurialShiyongJiaocheng/js/libs/jquery.min.js
MercurialShiyongJiaocheng/js/libs/localforage.min.js
mercurial_shiyong_jiaocheng-2024.2.29.0.dist-info/METADATA
mercurial_shiyong_jiaocheng-2024.2.29.0.dist-info/WHEEL
mercurial_shiyong_jiaocheng-2024.2.29.0.dist-info/entry_points.txt
mercurial_shiyong_jiaocheng-2024.2.29.0.dist-info/top_level.txt
mercurial_shiyong_jiaocheng-2024.2.29.0.dist-info/RECORD
